{
  "source_pdf": "Lunch_at_School.pdf",
  "pages": 9,
  "filter_mode": "primary-large-text",
  "requested_filter_mode": "primary-large-text",
  "effective_filter_mode": "primary-large-text",
  "min_font_size": 24,
  "ocr_mode": "auto",
  "extraction_engine": "paddleocr",
  "ocr_lang": "en",
  "ocr_dpi": 96,
  "blocks": [
    {
      "page": 2,
      "index": 0,
      "bbox": [
        110.25,
        409.5,
        367.5,
        464.25
      ],
      "text": "My friends.",
      "width": 257.25,
      "height": 54.75,
      "unit": "ocr-line",
      "max_font_size": 12.81,
      "ocr_confidence": 0.7842
    },
    {
      "page": 3,
      "index": 0,
      "bbox": [
        114,
        415.5,
        318,
        468.75
      ],
      "text": "My bag.",
      "width": 204,
      "height": 53.25,
      "unit": "ocr-line",
      "max_font_size": 14.91,
      "ocr_confidence": 0.7594
    },
    {
      "page": 4,
      "index": 0,
      "bbox": [
        108.75,
        417,
        314.25,
        464.25
      ],
      "text": "My milk.",
      "width": 205.5,
      "height": 47.25,
      "unit": "ocr-line",
      "max_font_size": 13.23,
      "ocr_confidence": 0.7707
    },
    {
      "page": 5,
      "index": 0,
      "bbox": [
        114.75,
        414.75,
        324.75,
        467.25
      ],
      "text": "My noodles.",
      "width": 210,
      "height": 52.5,
      "unit": "ocr-line",
      "max_font_size": 14.7,
      "ocr_confidence": 0.9935
    },
    {
      "page": 6,
      "index": 0,
      "bbox": [
        110.25,
        418.5,
        359.25,
        464.25
      ],
      "text": "My carrots.",
      "width": 249,
      "height": 45.75,
      "unit": "ocr-line",
      "max_font_size": 12.81,
      "ocr_confidence": 0.9172
    },
    {
      "page": 7,
      "index": 0,
      "bbox": [
        117,
        417,
        307.5,
        465
      ],
      "text": "My cookie.",
      "width": 190.5,
      "height": 48,
      "unit": "ocr-line",
      "max_font_size": 13.44,
      "ocr_confidence": 0.991
    },
    {
      "page": 8,
      "index": 0,
      "bbox": [
        106.5,
        407.25,
        351,
        469.5
      ],
      "text": "My napkin.",
      "width": 244.5,
      "height": 62.25,
      "unit": "ocr-line",
      "max_font_size": 15.75,
      "ocr_confidence": 0.8543
    },
    {
      "page": 9,
      "index": 0,
      "bbox": [
        116.25,
        408,
        340.5,
        465.75
      ],
      "text": "My lunch!",
      "width": 224.25,
      "height": 57.75,
      "unit": "ocr-line",
      "max_font_size": 13.65,
      "ocr_confidence": 0.8476
    }
  ]
}
